easy_amplicon/__init__.py
easy_amplicon/analysis.py
easy_amplicon/analysis_sintax.py
easy_amplicon/get_abundance.py
easy_amplicon/get_tree.py
easy_amplicon/isolate_plot.py
easy_amplicon/isolate_utils.py
easy_amplicon/plot.py
easy_amplicon/plot_dm.py
easy_amplicon/plot_tree.py
easy_amplicon/process_nbc_tax.py
easy_amplicon/process_queue.py
easy_amplicon/process_rrndb.py
easy_amplicon/reorder.py
easy_amplicon/run_rdp_classifier.py
easy_amplicon/trim.py
easy_amplicon/usearch_workflow.py
easy_amplicon/utils.py
easy_amplicon/utils_blast.py
easy_amplicon/data/conda_requirements.txt
easy_amplicon/data/isolate/barcode_layout.tsv
easy_amplicon/data/isolate/barcodes_fwd.fasta
easy_amplicon/data/isolate/barcodes_rev.fasta
easy_amplicon/data/isolate/barcodes_rev_es.fasta
easy_amplicon/data/isolate/patterns - Copy.txt:Zone.Identifier
easy_amplicon/data/isolate/patterns.txt
easy_amplicon/data/isolate/patterns_mmv.txt
easy_amplicon/data/maps_seq/BC1.fasta
easy_amplicon/data/maps_seq/BC2.fasta
easy_amplicon/data/maps_seq/BC3.fasta
easy_amplicon/read_processer/map_utils.py
easy_amplicon/read_processer/recording.py
easy_amplicon/setup/conda_install.py
easy_amplicon/setup/download_rdp.py
easy_amplicon/setup/download_test_data.py
easy_amplicon/setup/info.yaml
easy_amplicon-1.0.8.dist-info/METADATA
easy_amplicon-1.0.8.dist-info/WHEEL
easy_amplicon-1.0.8.dist-info/entry_points.txt
easy_amplicon-1.0.8.dist-info/RECORD
